pathsearch.py
pathsearch-1.1.4.dist-info/entry_points.txt
pathsearch-1.1.4.dist-info/LICENSE
pathsearch-1.1.4.dist-info/WHEEL
pathsearch-1.1.4.dist-info/METADATA
pathsearch-1.1.4.dist-info/RECORD
