Metadata-Version: 2.1
Name: pathsearch
Version: 1.1.4
Summary: A script to search for a file in a list of directories.
Home-page: https://github.com/mrlegohead0x45/pathsearch
License: MIT
Author: mrlegohead0x45
Author-email: mrlegohead0x45@gmail.com
Requires-Python: >=3.10,<4.0
Classifier: Development Status :: 5 - Production/Stable
Classifier: Environment :: Console
Classifier: Intended Audience :: Developers
Classifier: License :: OSI Approved :: MIT License
Classifier: Operating System :: OS Independent
Classifier: Programming Language :: Python :: 3
Classifier: Programming Language :: Python :: 3.10
Classifier: Topic :: Utilities
Project-URL: Repository, https://github.com/mrlegohead0x45/pathsearch
